comun_log.py
comun_log-0.6.dist-info/METADATA
comun_log-0.6.dist-info/WHEEL
comun_log-0.6.dist-info/top_level.txt
comun_log-0.6.dist-info/RECORD
