Metadata-Version: 2.1
Name: comun-log
Version: 0.6
Summary: UNKNOWN
Home-page: UNKNOWN
License: UNKNOWN
Platform: UNKNOWN
Requires-Dist: requests
